setup.py
dm/__init__.py
dm.zope.schema.egg-info/PKG-INFO
dm.zope.schema.egg-info/SOURCES.txt
dm.zope.schema.egg-info/dependency_links.txt
dm.zope.schema.egg-info/namespace_packages.txt
dm.zope.schema.egg-info/not-zip-safe
dm.zope.schema.egg-info/requires.txt
dm.zope.schema.egg-info/top_level.txt
dm/zope/__init__.py
dm/zope/schema/LICENSE.txt
dm/zope/schema/README.txt
dm/zope/schema/VERSION.txt
dm/zope/schema/__init__.py
dm/zope/schema/dataschema.py
dm/zope/schema/form.py
dm/zope/schema/interfaces.py
dm/zope/schema/overrides.zcml
dm/zope/schema/password.zcml
dm/zope/schema/propertymanager.py
dm/zope/schema/schema.py
dm/zope/schema/tag.py
dm/zope/schema/tests.py
dm/zope/schema/timedelta.zcml
dm/zope/schema/verify.py
dm/zope/schema/widget.py
dm/zope/schema/z2/__init__.py
dm/zope/schema/z2/constructor.py
dm/zope/schema/z2/form.py
dm/zope/schema/z2/form_template-4.pt
dm/zope/schema/z2/form_template.pt
dm/zope/schema/z2/schema.py
dm/zope/schema/z2/template.py
dm/zope/schema/z2/test/__init__.py
dm/zope/schema/z2/test/configure.zcml