Metadata-Version: 1.1
Name: dm.zope.schema
Version: 4.0
Summary: 'zope.schema' extensions
Home-page: https://pypi.org/project/dm.zope.schema
Author: Dieter Maurer
Author-email: dieter@handshake.de
License: ZPL
Keywords: application development zope schema
Platform: UNKNOWN
Classifier: Development Status :: 5 - Production/Stable
Classifier: Intended Audience :: Developers
Classifier: License :: OSI Approved :: Zope Public License
Classifier: Framework :: Zope
Classifier: Framework :: Zope :: 4
Classifier: Framework :: Zope2
Classifier: Operating System :: OS Independent
Classifier: Programming Language :: Python
Classifier: Programming Language :: Python :: 2.7
Classifier: Programming Language :: Python :: 3
Classifier: Topic :: Utilities
